unrealcv/__init__.py
unrealcv/api.py
unrealcv/automation.py
unrealcv/launcher.py
unrealcv/util.py
unrealcv-1.1.7.dist-info/METADATA
unrealcv-1.1.7.dist-info/WHEEL
unrealcv-1.1.7.dist-info/top_level.txt
unrealcv-1.1.7.dist-info/RECORD
