Metadata-Version: 2.1
Name: UnrealCV
Version: 1.1.7
Summary: UnrealCV client for python. see http://unrealcv.org for more detail.
Author: Hai Ci, Kui Wu
Author-email: Weichao Qiu <qiuwch@gmail.com>, Fangwei Zhong <zfw1226@gmail.com>
Project-URL: Homepage, http://unrealcv.org
Project-URL: Download, http://unrealcv.github.io
Keywords: computer vision,unreal engine,ue4/5,synthetic,simulator,robotics
Requires-Python: >=3.7
Requires-Dist: docker
Requires-Dist: opencv-python
Requires-Dist: pillow
Requires-Dist: numpy
